LICENSE
MANIFEST.in
README.rst
setup.cfg
setup.py
pyhacrf/__init__.py
pyhacrf/algorithms.c
pyhacrf/feature_extraction.py
pyhacrf/pyhacrf.py
pyhacrf/state_machine.py
pyhacrf.egg-info/PKG-INFO
pyhacrf.egg-info/SOURCES.txt
pyhacrf.egg-info/dependency_links.txt
pyhacrf.egg-info/requires.txt
pyhacrf.egg-info/top_level.txt