Metadata-Version: 1.1
Name: pyhacrf
Version: 0.1.1
Summary: Hidden alignment conditional random field, a discriminative string edit distance
Home-page: https://github.com/dirko/pyhacrf
Author: Dirko Coetsee
Author-email: dpcoetsee@gmail.com
License: BSD
Download-URL: https://github.com/dirko/pyhacrf/tarball/0.1.1
Platform: UNKNOWN
Classifier: Intended Audience :: Science/Research
Classifier: License :: OSI Approved :: BSD License
Classifier: Operating System :: OS Independent
Classifier: Programming Language :: Python
Classifier: Topic :: Scientific/Engineering
